watermark/__init__.py
watermark/__main__.py
watermark/cli.py
watermark/encoding.py
watermark/images.py
watermark/pdf.py
watermark/render.py
watermark/utils.py
watermarker_tool-0.1.3.dist-info/METADATA
watermarker_tool-0.1.3.dist-info/WHEEL
watermarker_tool-0.1.3.dist-info/entry_points.txt
watermarker_tool-0.1.3.dist-info/RECORD
