Metadata-Version: 2.4
Name: watermarker-tool
Version: 0.1.3
Summary: Add your description here
Requires-Python: >=3.11
Requires-Dist: pillow>=11.3.0
Requires-Dist: pymupdf>=1.26.4
